{
 "name": "Wizards Universal Filter",
 "children": [
  {
   "name": "Location",
   "children": [
    {
     "name": "TRT"
    },
    {
     "name": "World Regions"
    },
    {
     "name": "Country",
     "children": [
      {"name": "AspectRatioBanker", "size": 7074}
     ]
    },
    {
        "name": "SSD Territory"
    }
   ]
  },
  {
   "name": "People Leader",
   "children": [
    {
     "name": "All Leader Levels",
     "children": [
      {"name": "Level 1", "size": 1983},
      {"name": "Level 2", "size": 2047},
      {"name": "Level 3", "size": 1375},
      {"name": "Level 4", "size": 8746},
      {"name": "Level 5", "size": 8746}
     ]
    }
   ]
  },
  {
   "name": "Cost Center",
   "children": [
    {"name": "Cost Center Code", "size": 1759},
    {"name": "Cost Center Name", "size": 2165}
   ]
  },
  {
   "name": "Employee",
   "children": [
    {"name": "Employee Type", "size": 8833},
    {"name": "Employee Status", "size": 1732}
   ]
  },
  {
   "name": "Business Unit"
  }
  
 ]
}